{
    "type": "v8",
    "htmlPath": ".temp/monocart/coverage-f8ad4b6741d60f9e7b81/index.html",
    "watermarks": [
        50,
        80
    ],
    "summary": {
        "total": 1246658,
        "covered": 514528,
        "uncovered": 732130,
        "pct": 41.27,
        "status": "low"
    },
    "files": [
        {
            "name": "injectStylesIntoStyleTag.js",
            "type": "js",
            "url": "webpack://monocart-v8/starfall-cli/node_modules/style-loader/dist/runtime/injectStylesIntoStyleTag.js",
            "total": 2480,
            "covered": 1145,
            "uncovered": 1335,
            "pct": 46.17,
            "status": "low"
        },
        {
            "name": "bootstrap",
            "type": "js",
            "url": "webpack://fps-detector/webpack/bootstrap",
            "total": 52,
            "covered": 52,
            "uncovered": 0,
            "pct": 100,
            "status": "high"
        },
        {
            "name": "report.vue",
            "type": "js",
            "url": "webpack://monocart-v8/packages/v8/src/components/report.vue?8f96",
            "total": 1449,
            "covered": 1386,
            "uncovered": 63,
            "pct": 95.65,
            "status": "high"
        },
        {
            "name": "runtime-core.esm-bundler.js",
            "type": "js",
            "url": "webpack://monocart-v8/node_modules/@vue/runtime-core/dist/runtime-core.esm-bundler.js",
            "total": 316502,
            "covered": 108186,
            "uncovered": 208316,
            "pct": 34.18,
            "status": "low"
        },
        {
            "name": "external-umd-monocart-formatter",
            "type": "js",
            "url": "webpack://monocart-v8/external umd \"monocart-formatter\"",
            "total": 64,
            "covered": 64,
            "uncovered": 0,
            "pct": 100,
            "status": "high"
        },
        {
            "name": "setAttributesWithAttributesAndNonce.js",
            "type": "js",
            "url": "webpack://monocart-v8/starfall-cli/node_modules/style-loader/dist/runtime/setAttributesWithAttributesAndNonce.js",
            "total": 271,
            "covered": 271,
            "uncovered": 0,
            "pct": 100,
            "status": "high"
        },
        {
            "name": "demo.js",
            "type": "js",
            "url": "http://localhost:8090/demo/demo.js",
            "total": 830,
            "covered": 684,
            "uncovered": 146,
            "pct": 82.41,
            "status": "high"
        },
        {
            "name": "index.js",
            "type": "js",
            "url": "webpack://fps-detector/src/index.js",
            "total": 10310,
            "covered": 5453,
            "uncovered": 4857,
            "pct": 52.89,
            "status": "medium"
        },
        {
            "name": "flyover.vue",
            "type": "js",
            "url": "webpack://monocart-v8/packages/v8/src/components/flyover.vue?eba5",
            "total": 855,
            "covered": 855,
            "uncovered": 0,
            "pct": 100,
            "status": "high"
        },
        {
            "name": "style.css",
            "type": "css",
            "url": "http://localhost:8090/demo/style.css",
            "total": 189,
            "covered": 106,
            "uncovered": 83,
            "pct": 56.08,
            "status": "medium"
        },
        {
            "name": "report.vue",
            "type": "js",
            "url": "webpack://monocart-v8/packages/v8/src/components/report.vue?5281",
            "total": 482,
            "covered": 482,
            "uncovered": 0,
            "pct": 100,
            "status": "high"
        },
        {
            "name": "runtime-dom.esm-bundler.js",
            "type": "js",
            "url": "webpack://monocart-v8/node_modules/@vue/runtime-dom/dist/runtime-dom.esm-bundler.js",
            "total": 60425,
            "covered": 16559,
            "uncovered": 43866,
            "pct": 27.4,
            "status": "low"
        },
        {
            "name": "flyover.vue",
            "type": "js",
            "url": "webpack://monocart-v8/packages/v8/src/components/flyover.vue",
            "total": 1821,
            "covered": 1632,
            "uncovered": 189,
            "pct": 89.62,
            "status": "high"
        },
        {
            "name": "insertBySelector.js",
            "type": "js",
            "url": "webpack://monocart-v8/starfall-cli/node_modules/style-loader/dist/runtime/insertBySelector.js",
            "total": 1003,
            "covered": 492,
            "uncovered": 511,
            "pct": 49.05,
            "status": "low"
        },
        {
            "name": "store.js",
            "type": "js",
            "url": "webpack://monocart-v8/packages/app/src/common/store.js",
            "total": 450,
            "covered": 285,
            "uncovered": 165,
            "pct": 63.33,
            "status": "medium"
        },
        {
            "name": "report.vue",
            "type": "js",
            "url": "webpack://monocart-v8/packages/v8/src/components/report.vue?ac7d",
            "total": 1163,
            "covered": 1163,
            "uncovered": 0,
            "pct": 100,
            "status": "high"
        },
        {
            "name": "app.vue",
            "type": "js",
            "url": "webpack://monocart-v8/packages/v8/src/app.vue?73a8",
            "total": 314,
            "covered": 314,
            "uncovered": 0,
            "pct": 100,
            "status": "high"
        },
        {
            "name": "icon-label.vue",
            "type": "js",
            "url": "webpack://monocart-v8/packages/v8/src/components/icon-label.vue?9403",
            "total": 1147,
            "covered": 1147,
            "uncovered": 0,
            "pct": 100,
            "status": "high"
        },
        {
            "name": "shared.esm-bundler.js",
            "type": "js",
            "url": "webpack://monocart-v8/node_modules/@vue/shared/dist/shared.esm-bundler.js",
            "total": 23750,
            "covered": 15022,
            "uncovered": 8728,
            "pct": 63.25,
            "status": "medium"
        },
        {
            "name": "app.vue",
            "type": "js",
            "url": "webpack://monocart-v8/packages/v8/src/app.vue?ffe4",
            "total": 1419,
            "covered": 1356,
            "uncovered": 63,
            "pct": 95.56,
            "status": "high"
        },
        {
            "name": "turbogrid.js",
            "type": "js",
            "url": "webpack://monocart-v8/node_modules/turbogrid/dist/turbogrid.js",
            "total": 166081,
            "covered": 99357,
            "uncovered": 66724,
            "pct": 59.82,
            "status": "medium"
        },
        {
            "name": "icon-label.vue",
            "type": "js",
            "url": "webpack://monocart-v8/packages/v8/src/components/icon-label.vue?c39a",
            "total": 330,
            "covered": 330,
            "uncovered": 0,
            "pct": 100,
            "status": "high"
        },
        {
            "name": "global",
            "type": "js",
            "url": "webpack://monocart-v8/webpack/runtime/global",
            "total": 221,
            "covered": 48,
            "uncovered": 173,
            "pct": 21.72,
            "status": "low"
        },
        {
            "name": "icon-label.vue",
            "type": "js",
            "url": "webpack://monocart-v8/packages/v8/src/components/icon-label.vue",
            "total": 2820,
            "covered": 2529,
            "uncovered": 291,
            "pct": 89.68,
            "status": "high"
        },
        {
            "name": "index.js",
            "type": "js",
            "url": "webpack://monocart-v8/packages/v8/src/index.js",
            "total": 113,
            "covered": 113,
            "uncovered": 0,
            "pct": 100,
            "status": "high"
        },
        {
            "name": "flyover.vue",
            "type": "js",
            "url": "webpack://monocart-v8/packages/v8/src/components/flyover.vue?801b",
            "total": 538,
            "covered": 538,
            "uncovered": 0,
            "pct": 100,
            "status": "high"
        },
        {
            "name": "flyover.vue",
            "type": "js",
            "url": "webpack://monocart-v8/packages/v8/src/components/flyover.vue?e63d",
            "total": 484,
            "covered": 484,
            "uncovered": 0,
            "pct": 100,
            "status": "high"
        },
        {
            "name": "vue.runtime.esm-bundler.js",
            "type": "js",
            "url": "webpack://monocart-v8/node_modules/vue/dist/vue.runtime.esm-bundler.js",
            "total": 597,
            "covered": 306,
            "uncovered": 291,
            "pct": 51.26,
            "status": "medium"
        },
        {
            "name": "noSourceMaps.js",
            "type": "js",
            "url": "webpack://monocart-v8/starfall-cli/node_modules/css-loader/dist/runtime/noSourceMaps.js",
            "total": 64,
            "covered": 15,
            "uncovered": 49,
            "pct": 23.44,
            "status": "low"
        },
        {
            "name": "app.vue",
            "type": "js",
            "url": "webpack://monocart-v8/packages/v8/src/app.vue?fbaf",
            "total": 3915,
            "covered": 3915,
            "uncovered": 0,
            "pct": 100,
            "status": "high"
        },
        {
            "name": "icon-label.vue",
            "type": "js",
            "url": "webpack://monocart-v8/packages/v8/src/components/icon-label.vue?9377",
            "total": 490,
            "covered": 490,
            "uncovered": 0,
            "pct": 100,
            "status": "high"
        },
        {
            "name": "report.vue",
            "type": "js",
            "url": "webpack://monocart-v8/packages/v8/src/components/report.vue",
            "total": 15444,
            "covered": 1777,
            "uncovered": 13667,
            "pct": 11.51,
            "status": "low"
        },
        {
            "name": "report.vue",
            "type": "js",
            "url": "webpack://monocart-v8/packages/v8/src/components/report.vue?0b1e",
            "total": 533,
            "covered": 533,
            "uncovered": 0,
            "pct": 100,
            "status": "high"
        },
        {
            "name": "singletonStyleDomAPI.js",
            "type": "js",
            "url": "webpack://monocart-v8/starfall-cli/node_modules/style-loader/dist/runtime/singletonStyleDomAPI.js",
            "total": 2196,
            "covered": 1224,
            "uncovered": 972,
            "pct": 55.74,
            "status": "medium"
        },
        {
            "name": "flyover.vue",
            "type": "js",
            "url": "webpack://monocart-v8/packages/v8/src/components/flyover.vue?966f",
            "total": 477,
            "covered": 477,
            "uncovered": 0,
            "pct": 100,
            "status": "high"
        },
        {
            "name": "getUrl.js",
            "type": "js",
            "url": "webpack://monocart-v8/starfall-cli/node_modules/css-loader/dist/runtime/getUrl.js",
            "total": 597,
            "covered": 256,
            "uncovered": 341,
            "pct": 42.88,
            "status": "low"
        },
        {
            "name": "browser.js",
            "type": "js",
            "url": "http://localhost:8090/demo/browser.js",
            "total": 10582,
            "covered": 7373,
            "uncovered": 3209,
            "pct": 69.67,
            "status": "medium"
        },
        {
            "name": "flyover.vue",
            "type": "js",
            "url": "webpack://monocart-v8/packages/v8/src/components/flyover.vue?b7a1",
            "total": 1450,
            "covered": 1387,
            "uncovered": 63,
            "pct": 95.66,
            "status": "high"
        },
        {
            "name": "index.js",
            "type": "js",
            "url": "webpack://monocart-v8/node_modules/async-tick/src/index.js",
            "total": 1319,
            "covered": 272,
            "uncovered": 1047,
            "pct": 20.62,
            "status": "low"
        },
        {
            "name": "universalModuleDefinition",
            "type": "js",
            "url": "webpack://monocart-v8/webpack/universalModuleDefinition",
            "total": 705,
            "covered": 320,
            "uncovered": 385,
            "pct": 45.39,
            "status": "low"
        },
        {
            "name": "external-umd-monocart-code-viewer",
            "type": "js",
            "url": "webpack://monocart-v8/external umd \"monocart-code-viewer\"",
            "total": 66,
            "covered": 66,
            "uncovered": 0,
            "pct": 100,
            "status": "high"
        },
        {
            "name": "icon-label.vue",
            "type": "js",
            "url": "webpack://monocart-v8/packages/v8/src/components/icon-label.vue?a368",
            "total": 1453,
            "covered": 1390,
            "uncovered": 63,
            "pct": 95.66,
            "status": "high"
        },
        {
            "name": "bootstrap.min.css",
            "type": "css",
            "url": "http://localhost:8090/demo/dist/bootstrap.min.css",
            "total": 194898,
            "covered": 2725,
            "uncovered": 192173,
            "pct": 1.4,
            "status": "low"
        },
        {
            "name": "inflate.js",
            "type": "js",
            "url": "webpack://monocart-v8/node_modules/lz-utils/dist/inflate.js",
            "total": 3714,
            "covered": 3686,
            "uncovered": 28,
            "pct": 99.25,
            "status": "high"
        },
        {
            "name": "icon-label.vue",
            "type": "js",
            "url": "webpack://monocart-v8/packages/v8/src/components/icon-label.vue?028b",
            "total": 480,
            "covered": 480,
            "uncovered": 0,
            "pct": 100,
            "status": "high"
        },
        {
            "name": "app.vue",
            "type": "js",
            "url": "webpack://monocart-v8/packages/v8/src/app.vue",
            "total": 21422,
            "covered": 16406,
            "uncovered": 5016,
            "pct": 76.58,
            "status": "medium"
        },
        {
            "name": "icons.js",
            "type": "js",
            "url": "webpack://monocart-v8/packages/app/src/common/icons.js",
            "total": 486,
            "covered": 486,
            "uncovered": 0,
            "pct": 100,
            "status": "high"
        },
        {
            "name": "api.js",
            "type": "js",
            "url": "webpack://monocart-v8/starfall-cli/node_modules/css-loader/dist/runtime/api.js",
            "total": 2303,
            "covered": 298,
            "uncovered": 2005,
            "pct": 12.94,
            "status": "low"
        },
        {
            "name": "vine-ui.esm.js",
            "type": "js",
            "url": "webpack://monocart-v8/node_modules/vine-ui/dist/vine-ui.esm.js",
            "total": 77126,
            "covered": 48007,
            "uncovered": 29119,
            "pct": 62.24,
            "status": "medium"
        },
        {
            "name": "app.vue",
            "type": "js",
            "url": "webpack://monocart-v8/packages/v8/src/app.vue?7298",
            "total": 458,
            "covered": 458,
            "uncovered": 0,
            "pct": 100,
            "status": "high"
        },
        {
            "name": "share.js",
            "type": "js",
            "url": "webpack://monocart-v8/lib/platform/share.js",
            "total": 9347,
            "covered": 4063,
            "uncovered": 5284,
            "pct": 43.47,
            "status": "low"
        },
        {
            "name": "make-namespace-object",
            "type": "js",
            "url": "webpack://fps-detector/webpack/runtime/make namespace object",
            "total": 274,
            "covered": 274,
            "uncovered": 0,
            "pct": 100,
            "status": "high"
        },
        {
            "name": "exportHelper.js",
            "type": "js",
            "url": "webpack://monocart-v8/starfall-cli/node_modules/vue-loader/dist/exportHelper.js",
            "total": 328,
            "covered": 328,
            "uncovered": 0,
            "pct": 100,
            "status": "high"
        },
        {
            "name": "redirection.js",
            "type": "js",
            "url": "http://localhost:8090/demo/redirection.js",
            "total": 6507,
            "covered": 4575,
            "uncovered": 1932,
            "pct": 70.31,
            "status": "medium"
        },
        {
            "name": "reactivity.esm-bundler.js",
            "type": "js",
            "url": "webpack://monocart-v8/node_modules/@vue/reactivity/dist/reactivity.esm-bundler.js",
            "total": 42949,
            "covered": 20553,
            "uncovered": 22396,
            "pct": 47.85,
            "status": "low"
        },
        {
            "name": "icon-label.vue",
            "type": "js",
            "url": "webpack://monocart-v8/packages/v8/src/components/icon-label.vue?5065",
            "total": 553,
            "covered": 553,
            "uncovered": 0,
            "pct": 100,
            "status": "high"
        },
        {
            "name": "report.vue",
            "type": "js",
            "url": "webpack://monocart-v8/packages/v8/src/components/report.vue?149d",
            "total": 326,
            "covered": 326,
            "uncovered": 0,
            "pct": 100,
            "status": "high"
        },
        {
            "name": "define-property-getters",
            "type": "js",
            "url": "webpack://monocart-v8/webpack/runtime/define property getters",
            "total": 308,
            "covered": 308,
            "uncovered": 0,
            "pct": 100,
            "status": "high"
        },
        {
            "name": "hash.js",
            "type": "js",
            "url": "webpack://monocart-v8/packages/app/src/common/hash.js",
            "total": 1037,
            "covered": 219,
            "uncovered": 818,
            "pct": 21.12,
            "status": "low"
        },
        {
            "name": "define-property-getters",
            "type": "js",
            "url": "webpack://fps-detector/webpack/runtime/define property getters",
            "total": 308,
            "covered": 308,
            "uncovered": 0,
            "pct": 100,
            "status": "high"
        },
        {
            "name": "hasOwnProperty-shorthand",
            "type": "js",
            "url": "webpack://fps-detector/webpack/runtime/hasOwnProperty shorthand",
            "total": 88,
            "covered": 88,
            "uncovered": 0,
            "pct": 100,
            "status": "high"
        },
        {
            "name": "flyover.vue",
            "type": "js",
            "url": "webpack://monocart-v8/packages/v8/src/components/flyover.vue?1d68",
            "total": 327,
            "covered": 327,
            "uncovered": 0,
            "pct": 100,
            "status": "high"
        },
        {
            "name": "insertStyleElement.js",
            "type": "js",
            "url": "webpack://monocart-v8/starfall-cli/node_modules/style-loader/dist/runtime/insertStyleElement.js",
            "total": 285,
            "covered": 285,
            "uncovered": 0,
            "pct": 100,
            "status": "high"
        },
        {
            "name": "bootstrap",
            "type": "js",
            "url": "webpack://monocart-v8/webpack/bootstrap",
            "total": 621,
            "covered": 621,
            "uncovered": 0,
            "pct": 100,
            "status": "high"
        },
        {
            "name": "-sync-.svg$",
            "type": "js",
            "url": "webpack://monocart-v8/packages/v8/src/images/icons/ sync \\.svg$",
            "total": 692,
            "covered": 551,
            "uncovered": 141,
            "pct": 79.62,
            "status": "medium"
        },
        {
            "name": "compat-get-default-export",
            "type": "js",
            "url": "webpack://monocart-v8/webpack/runtime/compat get default export",
            "total": 267,
            "covered": 238,
            "uncovered": 29,
            "pct": 89.14,
            "status": "high"
        },
        {
            "name": "app.vue",
            "type": "js",
            "url": "webpack://monocart-v8/packages/v8/src/app.vue?71dc",
            "total": 507,
            "covered": 507,
            "uncovered": 0,
            "pct": 100,
            "status": "high"
        },
        {
            "name": "universalModuleDefinition",
            "type": "js",
            "url": "webpack://fps-detector/webpack/universalModuleDefinition",
            "total": 388,
            "covered": 263,
            "uncovered": 125,
            "pct": 67.78,
            "status": "medium"
        },
        {
            "name": "report.vue",
            "type": "js",
            "url": "webpack://monocart-v8/packages/v8/src/components/report.vue?94fa",
            "total": 476,
            "covered": 476,
            "uncovered": 0,
            "pct": 100,
            "status": "high"
        },
        {
            "name": "make-namespace-object",
            "type": "js",
            "url": "webpack://monocart-v8/webpack/runtime/make namespace object",
            "total": 274,
            "covered": 274,
            "uncovered": 0,
            "pct": 100,
            "status": "high"
        },
        {
            "name": "ie-polyfill.js",
            "type": "js",
            "url": "http://localhost:8090/demo/ie-polyfill.js",
            "total": 238107,
            "covered": 121935,
            "uncovered": 116172,
            "pct": 51.21,
            "status": "medium"
        },
        {
            "name": "app.vue",
            "type": "js",
            "url": "webpack://monocart-v8/packages/v8/src/app.vue?5cc4",
            "total": 464,
            "covered": 464,
            "uncovered": 0,
            "pct": 100,
            "status": "high"
        },
        {
            "name": "hasOwnProperty-shorthand",
            "type": "js",
            "url": "webpack://monocart-v8/webpack/runtime/hasOwnProperty shorthand",
            "total": 88,
            "covered": 88,
            "uncovered": 0,
            "pct": 100,
            "status": "high"
        },
        {
            "name": "util.js",
            "type": "js",
            "url": "webpack://monocart-v8/packages/v8/src/utils/util.js",
            "total": 409,
            "covered": 281,
            "uncovered": 128,
            "pct": 68.7,
            "status": "medium"
        },
        {
            "name": "demo",
            "type": "js",
            "url": "http://localhost:8090/demo/",
            "total": 139,
            "covered": 139,
            "uncovered": 0,
            "pct": 100,
            "status": "high"
        },
        {
            "name": "coverage-data.js",
            "type": "js",
            "url": "http://localhost:8090/demo/dist/coverage-data.js",
            "total": 4033,
            "covered": 4033,
            "uncovered": 0,
            "pct": 100,
            "status": "high"
        },
        {
            "name": "microtask.js",
            "type": "js",
            "url": "webpack://monocart-v8/node_modules/async-tick/src/microtask.js",
            "total": 1218,
            "covered": 51,
            "uncovered": 1167,
            "pct": 4.19,
            "status": "low"
        }
    ]
}
